{
  "citation": {
    "type": "source",
    "source_id": "openalex:W2498762694",
    "canonical_url": "https://openalex.org/W2498762694",
    "title": "Catalytic One\u2010Pot Diastereoselective Michael\u2010Initiated Ring\u2010Closure of Methyl Ketones with 3\u2010Bromochromones: Synthesis of Cyclopropa[<i>b</i>]chromanones",
    "authors": [
      "Joana L. C. Sousa",
      "Oualid Talhi",
      "Ricardo F. Mendes",
      "Filipe A. Almeida Paz",
      "Khaldoun Bachar\u0131",
      "Artur M. S. Silva"
    ],
    "year": 2016,
    "doi": "https://doi.org/10.1002/ejoc.201600413",
    "provider_url": "https://openalex.org/",
    "license": "CC0"
  },
  "data": {
    "cited_by_count": 9,
    "type": "article",
    "venue": "European Journal of Organic Chemistry",
    "concepts": [
      "Chemistry",
      "Cyclopropane",
      "Ring (chemistry)",
      "Michael reaction",
      "Stereochemistry"
    ],
    "oa_status": "closed"
  },
  "receipt": {
    "tier": "seed",
    "source": "openalex-author-filter",
    "fetched_at": "2026-04-23T03:17:23Z"
  }
}